pyorb/__init__.py
pyorb/_const_docs.py
pyorb/const.py
pyorb/kepler.py
pyorb/orbit.py
pyorb/unit.py
pyorb/version.py
pyorb-0.6.0.dist-info/LICENSE
pyorb-0.6.0.dist-info/METADATA
pyorb-0.6.0.dist-info/WHEEL
pyorb-0.6.0.dist-info/top_level.txt
pyorb-0.6.0.dist-info/RECORD
