Metadata-Version: 2.1
Name: pyorb
Version: 0.6.0
Summary: Keplerian orbit functions in Python
Author: Daniel Kastinen
Author-email: daniel.kastinen@irf.se
License: MIT
Classifier: Intended Audience :: Science/Research
Classifier: Programming Language :: Python :: 3
Classifier: Topic :: Scientific/Engineering :: Physics
Classifier: Operating System :: OS Independent
Classifier: License :: OSI Approved :: MIT License
Requires-Python: >=3.0
License-File: LICENSE
Requires-Dist: numpy >=1.18.4
Provides-Extra: develop
Requires-Dist: pytest >=6.2.5 ; extra == 'develop'
Requires-Dist: sphinx >=4.2.0 ; extra == 'develop'
Requires-Dist: flake8 >=4.0.1 ; extra == 'develop'
Requires-Dist: wheel >=0.37.0 ; extra == 'develop'
Requires-Dist: build >=0.7.0 ; extra == 'develop'
Requires-Dist: twine >=3.4.2 ; extra == 'develop'
Requires-Dist: pytest-cov >=4.1.0 ; extra == 'develop'
Requires-Dist: sphinx-gallery >=0.3.1 ; extra == 'develop'
Requires-Dist: matplotlib >=3.5.1 ; extra == 'develop'
Requires-Dist: nbsphinx >=0.8.8 ; extra == 'develop'
Requires-Dist: ipykernel >=6.9.1 ; extra == 'develop'
Requires-Dist: radon >=5.1.0 ; extra == 'develop'
Requires-Dist: numpydoc >=1.2 ; extra == 'develop'
Requires-Dist: pre-commit >3.0.0 ; extra == 'develop'
Requires-Dist: black >=23.3.0 ; extra == 'develop'
